[
  {
    "spdx": "MIT",
    "name": "MIT License",
    "url": "https://raw.githubusercontent.com/spdx/license-list-data/master/text/MIT.txt",
    "sha256": "b05785f9f18e6716bab63424b11454513b9943a222595b70411009202fc592b5",
    "template": {
      "fields": [
        "years",
        "name"
      ],
      "replacements": [
        {
          "field": "years",
          "start": 27,
          "end": 33
        },
        {
          "field": "name",
          "start": 34,
          "end": 53
        }
      ]
    }
  },
  {
    "spdx": "Apache-2.0",
    "name": "Apache License 2.0",
    "url": "https://raw.githubusercontent.com/spdx/license-list-data/master/text/Apache-2.0.txt",
    "sha256": "074e6e32c86a4c0ef8b3ed25b721ca23aca83df277cd88106ef7177c354615ff",
    "template": {
      "fields": [
        "years",
        "name"
      ],
      "replacements": [
        {
          "field": "years",
          "start": 9726,
          "end": 9732
        },
        {
          "field": "name",
          "start": 9733,
          "end": 9758
        }
      ]
    }
  },
  {
    "spdx": "BSD-3-Clause",
    "name": "BSD 3-Clause License",
    "url": "https://raw.githubusercontent.com/spdx/license-list-data/master/text/BSD-3-Clause.txt",
    "sha256": "5a93d5831e1297ab10fe643e1a631e83be392896da14ee2951285a79012df69d",
    "template": {
      "fields": [
        "years",
        "name"
      ],
      "replacements": [
        {
          "field": "years",
          "start": 14,
          "end": 20
        },
        {
          "field": "name",
          "start": 21,
          "end": 28
        }
      ]
    }
  },
  {
    "spdx": "BSD-2-Clause",
    "name": "BSD 2-Clause License",
    "url": "https://raw.githubusercontent.com/spdx/license-list-data/master/text/BSD-2-Clause.txt",
    "sha256": "f32fb3b417a194167cfad068223fc975ba96c5960513a10f66a3c28720aec1df",
    "template": {
      "fields": [
        "years",
        "name"
      ],
      "replacements": [
        {
          "field": "years",
          "start": 14,
          "end": 20
        },
        {
          "field": "name",
          "start": 21,
          "end": 28
        }
      ]
    }
  },
  {
    "spdx": "ISC",
    "name": "ISC License",
    "url": "https://raw.githubusercontent.com/spdx/license-list-data/master/text/ISC.txt",
    "sha256": "f2ec607f67bb0dd3053b49835b02110d5cd0f8eb6da3aac4dc0b142a6b299be9"
  },
  {
    "spdx": "MPL-2.0",
    "name": "Mozilla Public License 2.0",
    "url": "https://raw.githubusercontent.com/spdx/license-list-data/master/text/MPL-2.0.txt",
    "sha256": "66a3107d5ad6a058aab753eaac2047ccb2ed0e39465dd0fe5844da3e300d5172"
  },
  {
    "spdx": "LGPL-3.0-only",
    "name": "GNU Lesser General Public License v3.0 only",
    "url": "https://raw.githubusercontent.com/spdx/license-list-data/master/text/LGPL-3.0-only.txt",
    "sha256": "996af0513df21f7496288951c41428a03c174e9e4a9d63665c57d670f845ccb1"
  },
  {
    "spdx": "GPL-3.0-only",
    "name": "GNU General Public License v3.0 only",
    "url": "https://raw.githubusercontent.com/spdx/license-list-data/master/text/GPL-3.0-only.txt",
    "sha256": "fb981668c18a279e285fc4d83fba1e836cc84dd4daa73c9697d3cfd2d8aca6e0"
  },
  {
    "spdx": "GPL-3.0-or-later",
    "name": "GNU General Public License v3.0 or later",
    "url": "https://raw.githubusercontent.com/spdx/license-list-data/master/text/GPL-3.0-or-later.txt",
    "sha256": "fb981668c18a279e285fc4d83fba1e836cc84dd4daa73c9697d3cfd2d8aca6e0"
  },
  {
    "spdx": "Unlicense",
    "name": "The Unlicense",
    "url": "https://raw.githubusercontent.com/spdx/license-list-data/master/text/Unlicense.txt",
    "sha256": "0bdebfeda07d45dada625ae1317c6f833186e798b171d0db640bcf32e92a8240"
  }
]
